{
  "basics": {
    "name": "John Doe",
    "label": "Software Developer",
    "email": "john.doe@example.com",
    "phone": "123-456-7890",
    "summary": "---\n\n**Jared Graham**  \n**Senior Frontend Engineer**  \nGitHub: [Your GitHub]  \nLinkedIn: [Your LinkedIn]  \nWebsite: [Your Portfolio Website]  \nContact: 781-336-7247\n\n---\n\n### **Professional Summary**\n\nHighly skilled Frontend Engineer with over 5 years of experience in developing robust web applications using TypeScript, React, and Next.js. Adept at boosting user engagement through intuitive UI/UX design and rigorous performance optimization. Passionate about the blockchain industry and leveraging Web3 technologies to build innovative financial solutions. Proven track record of cross-functional collaboration and delivering customer-focused products.\n\n---\n\n### **Technical Skills**\n\n- **Programming Languages:** HTML, CSS, JavaScript, TypeScript, Python (with experience in Pandas)\n- **Frameworks & Libraries:** React, Next.js, Redux, Node.js, Express, Tailwind CSS, GraphQL\n- **Databases & Tools:** MongoDB, Firebase, Git, AWS\n- **Design Principles:** UX/UI Design, SEO, Prompt Engineering\n- **Optional Skills:** Knowledge of Go, experience with blockchain technology\n\n---\n\n### **Professional Experience**\n\n**Full-Stack Dating App**  \n*Role: Lead Frontend Developer*  \n*Technologies Used: React, Authentication, Websockets*\n\n- Developed a complete user interface for a dating app using React and Websockets, ensuring real-time updates and smooth performance.\n- Implemented robust authentication mechanisms enhancing user data security.\n- Collaborated with the backend team to integrate API endpoints and ensure seamless data flow between client and server.\n- Designed and implemented scalable front-end architecture to support future growth and feature expansion.\n\n**Crypto Trading Bot**  \n*Role: Developer*  \n*Technologies Used: Python, Pandas, Coinbase API*\n\n- Created a trading bot capable of executing cryptocurrency trades autonomously using Python and Coinbase API.\n- Analyzed historical trading data with Pandas to optimize trading strategies and performance.\n- Implemented logging and alerting mechanisms to monitor bot actions and track performance metrics.\n- Successfully tested and deployed the bot, achieving a notable enhancement in automated trading efficiency.\n\n---\n\n### **Education**\n\n**Bachelor’s Degree in Computer Science**  \n[Your University]  \n[Year of Graduation]\n\n---\n\n### **Certifications & Additional Training**\n\n- [Relevant Certification 1]\n- [Relevant Certification 2]\n- [Relevant Training]\n\n---\n\n### **Professional Interests**\n\n- Passionate about blockchain and Web3 technologies.\n- Motivated by the challenge of creating innovative financial products.\n- Enthusiastic about developing customer-focused applications and internal admin tools.\n\n---\n\n### **Location**\n\nEast Coast, North America\n\n---\n\n### **Projects/Contributions**\n\n- **Node API and Staking Products:** Developed and maintained frontend components for internal and customer-facing tools.\n- **Component Library:** Collaborated with UI team to implement a new component library, ensuring consistency and reusability across applications.\n- **UI/UX Design Feasibility:** Worked with designers to ensure that technical implementations were feasible and aligned with design requirements.\n- **Performance Monitoring:** Regularly monitored frontend app performance, identified bottlenecks, and implemented solutions to address any issues.\n\n---\n\n### **References**\n\nAvailable upon request.\n\n---\n\n**Note:** Benefits such as competitive salary, health insurance, remote work opportunities, and more are highly appealing and align perfectly with my career goals and work-life balance aspirations. \n\n---\n\n*For more details about my projects or to view my portfolio, please visit [JaredGraham.com].*",
    "location": {
      "address": "123 Main St",
      "city": "Anytown",
      "postalCode": "12345",
      "countryCode": "US"
    }
  },
  "work": [],
  "education": [],
  "skills": [],
  "languages": [],
  "interests": []
}